tasks_generator/__init__.py
tasks_generator/super_functions.py
tasks_generator/tasks_generator.py
tasks_generator_new-0.0.1.dist-info/LICENSE
tasks_generator_new-0.0.1.dist-info/METADATA
tasks_generator_new-0.0.1.dist-info/WHEEL
tasks_generator_new-0.0.1.dist-info/top_level.txt
tasks_generator_new-0.0.1.dist-info/RECORD
